django_rq_cron/__init__.py
django_rq_cron/admin.py
django_rq_cron/apps.py
django_rq_cron/models.py
django_rq_cron/registry.py
django_rq_cron/runner.py
django_rq_cron/utils.py
django_rq_cron/crons/__init__.py
django_rq_cron/crons/cleanup_old_runs.py
django_rq_cron/crons/ping.py
django_rq_cron/management/__init__.py
django_rq_cron/management/commands/__init__.py
django_rq_cron/management/commands/bootstrap_cron_jobs.py
django_rq_cron/migrations/0001_initial.py
django_rq_cron/migrations/__init__.py
django_rq_cron/tests/__init__.py
django_rq_cron/tests/test_registry.py
django_rq_cron/tests/test_runner.py
django_rq_cron-0.1.1.dist-info/licenses/LICENSE
tests/__init__.py
tests/settings.py
tests/urls.py
django_rq_cron-0.1.1.dist-info/METADATA
django_rq_cron-0.1.1.dist-info/WHEEL
django_rq_cron-0.1.1.dist-info/top_level.txt
django_rq_cron-0.1.1.dist-info/RECORD
